pyxargs.py
pyxargs-3.4.6.dist-info/LICENSE
pyxargs-3.4.6.dist-info/METADATA
pyxargs-3.4.6.dist-info/WHEEL
pyxargs-3.4.6.dist-info/entry_points.txt
pyxargs-3.4.6.dist-info/top_level.txt
pyxargs-3.4.6.dist-info/RECORD
